package com.google.android.gms.maps.model.internal;

import android.os.IBinder;
import android.os.Parcel;
import android.os.RemoteException;
import com.google.android.gms.dynamic.d;
import com.google.android.gms.dynamic.d.a;

class g$a$a
  implements g
{
  private IBinder le;
  
  g$a$a(IBinder paramIBinder)
  {
    le = paramIBinder;
  }
  
  public IBinder asBinder()
  {
    return le;
  }
  
  /* Error */
  public d b(android.graphics.Bitmap paramBitmap)
    throws RemoteException
  {
    // Byte code:
    //   0: invokestatic 31	android/os/Parcel:obtain	()Landroid/os/Parcel;
    //   3: astore_2
    //   4: invokestatic 31	android/os/Parcel:obtain	()Landroid/os/Parcel;
    //   7: astore_3
    //   8: aload_2
    //   9: ldc 33
    //   11: invokevirtual 37	android/os/Parcel:writeInterfaceToken	(Ljava/lang/String;)V
    //   14: aload_1
    //   15: ifnull +51 -> 66
    //   18: aload_2
    //   19: iconst_1
    //   20: invokevirtual 41	android/os/Parcel:writeInt	(I)V
    //   23: aload_1
    //   24: aload_2
    //   25: iconst_0
    //   26: invokevirtual 47	android/graphics/Bitmap:writeToParcel	(Landroid/os/Parcel;I)V
    //   29: aload_0
    //   30: getfield 18	com/google/android/gms/maps/model/internal/g$a$a:le	Landroid/os/IBinder;
    //   33: bipush 6
    //   35: aload_2
    //   36: aload_3
    //   37: iconst_0
    //   38: invokeinterface 53 5 0
    //   43: pop
    //   44: aload_3
    //   45: invokevirtual 56	android/os/Parcel:readException	()V
    //   48: aload_3
    //   49: invokevirtual 59	android/os/Parcel:readStrongBinder	()Landroid/os/IBinder;
    //   52: invokestatic 65	com/google/android/gms/dynamic/d$a:ap	(Landroid/os/IBinder;)Lcom/google/android/gms/dynamic/d;
    //   55: astore_1
    //   56: aload_3
    //   57: invokevirtual 68	android/os/Parcel:recycle	()V
    //   60: aload_2
    //   61: invokevirtual 68	android/os/Parcel:recycle	()V
    //   64: aload_1
    //   65: areturn
    //   66: aload_2
    //   67: iconst_0
    //   68: invokevirtual 41	android/os/Parcel:writeInt	(I)V
    //   71: goto -42 -> 29
    //   74: astore_1
    //   75: aload_3
    //   76: invokevirtual 68	android/os/Parcel:recycle	()V
    //   79: aload_2
    //   80: invokevirtual 68	android/os/Parcel:recycle	()V
    //   83: aload_1
    //   84: athrow
    // Local variable table:
    //   start	length	slot	name	signature
    //   0	85	0	this	a
    //   0	85	1	paramBitmap	android.graphics.Bitmap
    //   3	77	2	localParcel1	Parcel
    //   7	69	3	localParcel2	Parcel
    // Exception table:
    //   from	to	target	type
    //   8	14	74	finally
    //   18	29	74	finally
    //   29	56	74	finally
    //   66	71	74	finally
  }
  
  public d c(float paramFloat)
    throws RemoteException
  {
    Parcel localParcel1 = Parcel.obtain();
    Parcel localParcel2 = Parcel.obtain();
    try
    {
      localParcel1.writeInterfaceToken("com.google.android.gms.maps.model.internal.IBitmapDescriptorFactoryDelegate");
      localParcel1.writeFloat(paramFloat);
      le.transact(5, localParcel1, localParcel2, 0);
      localParcel2.readException();
      d locald = d.a.ap(localParcel2.readStrongBinder());
      return locald;
    }
    finally
    {
      localParcel2.recycle();
      localParcel1.recycle();
    }
  }
  
  public d cd(String paramString)
    throws RemoteException
  {
    Parcel localParcel1 = Parcel.obtain();
    Parcel localParcel2 = Parcel.obtain();
    try
    {
      localParcel1.writeInterfaceToken("com.google.android.gms.maps.model.internal.IBitmapDescriptorFactoryDelegate");
      localParcel1.writeString(paramString);
      le.transact(2, localParcel1, localParcel2, 0);
      localParcel2.readException();
      paramString = d.a.ap(localParcel2.readStrongBinder());
      return paramString;
    }
    finally
    {
      localParcel2.recycle();
      localParcel1.recycle();
    }
  }
  
  public d ce(String paramString)
    throws RemoteException
  {
    Parcel localParcel1 = Parcel.obtain();
    Parcel localParcel2 = Parcel.obtain();
    try
    {
      localParcel1.writeInterfaceToken("com.google.android.gms.maps.model.internal.IBitmapDescriptorFactoryDelegate");
      localParcel1.writeString(paramString);
      le.transact(3, localParcel1, localParcel2, 0);
      localParcel2.readException();
      paramString = d.a.ap(localParcel2.readStrongBinder());
      return paramString;
    }
    finally
    {
      localParcel2.recycle();
      localParcel1.recycle();
    }
  }
  
  public d cf(String paramString)
    throws RemoteException
  {
    Parcel localParcel1 = Parcel.obtain();
    Parcel localParcel2 = Parcel.obtain();
    try
    {
      localParcel1.writeInterfaceToken("com.google.android.gms.maps.model.internal.IBitmapDescriptorFactoryDelegate");
      localParcel1.writeString(paramString);
      le.transact(7, localParcel1, localParcel2, 0);
      localParcel2.readException();
      paramString = d.a.ap(localParcel2.readStrongBinder());
      return paramString;
    }
    finally
    {
      localParcel2.recycle();
      localParcel1.recycle();
    }
  }
  
  public d fo(int paramInt)
    throws RemoteException
  {
    Parcel localParcel1 = Parcel.obtain();
    Parcel localParcel2 = Parcel.obtain();
    try
    {
      localParcel1.writeInterfaceToken("com.google.android.gms.maps.model.internal.IBitmapDescriptorFactoryDelegate");
      localParcel1.writeInt(paramInt);
      le.transact(1, localParcel1, localParcel2, 0);
      localParcel2.readException();
      d locald = d.a.ap(localParcel2.readStrongBinder());
      return locald;
    }
    finally
    {
      localParcel2.recycle();
      localParcel1.recycle();
    }
  }
  
  public d ok()
    throws RemoteException
  {
    Parcel localParcel1 = Parcel.obtain();
    Parcel localParcel2 = Parcel.obtain();
    try
    {
      localParcel1.writeInterfaceToken("com.google.android.gms.maps.model.internal.IBitmapDescriptorFactoryDelegate");
      le.transact(4, localParcel1, localParcel2, 0);
      localParcel2.readException();
      d locald = d.a.ap(localParcel2.readStrongBinder());
      return locald;
    }
    finally
    {
      localParcel2.recycle();
      localParcel1.recycle();
    }
  }
}

/* Location:
 * Qualified Name:     com.google.android.gms.maps.model.internal.g.a.a
 * Java Class Version: 6 (50.0)
 * JD-Core Version:    0.7.1
 */